color.py
instream.py
outstream.py
picture.py
stdarray.py
stdaudio.py
stddraw.py
stdio.py
stdrandom.py
stdstats.py
su_stdlibs_python-0.0.2.dist-info/LICENSE
su_stdlibs_python-0.0.2.dist-info/METADATA
su_stdlibs_python-0.0.2.dist-info/WHEEL
su_stdlibs_python-0.0.2.dist-info/top_level.txt
su_stdlibs_python-0.0.2.dist-info/RECORD
